sharpfed/__init__.py
sharpfed/core.py
sharpfed-0.0.3.dist-info/LICENSE
sharpfed-0.0.3.dist-info/METADATA
sharpfed-0.0.3.dist-info/WHEEL
sharpfed-0.0.3.dist-info/top_level.txt
sharpfed-0.0.3.dist-info/RECORD
