Metadata-Version: 2.1
Name: sharpfed
Version: 0.0.3
Summary: Fast and easy federated learning framework based on Tensorflow
Home-page: https://github.com/WhatIsSurprise/SharpFed
Author: wangshuo
Author-email: shuowan16@163.com
Classifier: Programming Language :: Python :: 3
Classifier: License :: OSI Approved :: MIT License
Classifier: Operating System :: OS Independent
Requires-Python: <=3.8.10
License-File: LICENSE
